{
    "services": [
        {
            "name": "Установка",
            "subServices": [
                {"name": "Видео инструкция", "web": "https://t.me/StylishAntelopeFiles/33", "but": "2"}
            ]
        },
        {
            "name": "Скачать",
            "subServices": [
                {"name": "Advance Steel 2026", "web": "https://t.me/StylishAntelopeFiles/108", "but": "1"},
                {"name": "Advance Steel 2025", "web": "https://t.me/StylishAntelopeFiles/107", "but": "1"},
                {"name": "Advance Steel 2024", "web": "https://t.me/StylishAntelopeFiles/106", "but": "1"},
                {"name": "Advance Steel 2023", "web": "https://t.me/StylishAntelopeFiles/105", "but": "1"},
                {"name": "Advance Steel 2022", "web": "https://t.me/StylishAntelopeFiles/104", "but": "1"},
                {"name": "Advance Steel 2021", "web": "https://t.me/StylishAntelopeFiles/103", "but": "1"},
                {"name": "Advance Steel 2020", "web": "https://t.me/StylishAntelopeFiles/101", "but": "1"}
            ]
        },
        {
            "name": "Дополнительно",
            "subServices": [
                {"name": "Активатор Autodesk", "web": "https://t.me/StylishAntelopeFiles/155", "but": "3"}
            ]
        }
    ]
}
