{
    "services": [
        {
            "name": "Установка",
            "subServices": [
                {"name": "Видео инструкция", "web": "https://t.me/StylishAntelopeFiles/33", "but": "2"}
            ]
        },
        {
            "name": "Скачать",
            "subServices": [
                {"name": "Alias AutoStudio 2026", "web": "https://t.me/StylishAntelopeFiles/136", "but": "1"},
                {"name": "Alias AutoStudio 2025", "web": "https://t.me/StylishAntelopeFiles/134", "but": "1"},
                {"name": "Alias AutoStudio 2024", "web": "https://t.me/StylishAntelopeFiles/132", "but": "1"},
                {"name": "Alias AutoStudio 2023", "web": "https://t.me/StylishAntelopeFiles/130", "but": "1"}
            ]
        },
        {
            "name": "Дополнительно",
            "subServices": [
                {"name": "Активатор Autodesk", "web": "https://t.me/StylishAntelopeFiles/155", "but": "3"}
            ]
        }
    ]
}
